rust_crate_pipeline/__init__.py
rust_crate_pipeline/__main__.py
rust_crate_pipeline/ai_processing.py
rust_crate_pipeline/analysis.py
rust_crate_pipeline/common_types.py
rust_crate_pipeline/config.py
rust_crate_pipeline/config_loader.py
rust_crate_pipeline/crate_analysis.py
rust_crate_pipeline/crate_compilation.py
rust_crate_pipeline/crate_environment.py
rust_crate_pipeline/exceptions.py
rust_crate_pipeline/github_token_checker.py
rust_crate_pipeline/llm_client.py
rust_crate_pipeline/llm_factory.py
rust_crate_pipeline/llm_utils.py
rust_crate_pipeline/main.py
rust_crate_pipeline/network.py
rust_crate_pipeline/observability.py
rust_crate_pipeline/pipeline.py
rust_crate_pipeline/pipeline_analysis.py
rust_crate_pipeline/pipeline_enrichment.py
rust_crate_pipeline/pipeline_helpers.py
rust_crate_pipeline/post_install.py
rust_crate_pipeline/production_config.py
rust_crate_pipeline/progress_monitor.py
rust_crate_pipeline/schemas.py
rust_crate_pipeline/setup_manager.py
rust_crate_pipeline/unified_llm_processor.py
rust_crate_pipeline/unified_pipeline.py
rust_crate_pipeline/version.py
rust_crate_pipeline/audits/__init__.py
rust_crate_pipeline/audits/validate_db_hash.py
rust_crate_pipeline/core/__init__.py
rust_crate_pipeline/core/canon_registry.py
rust_crate_pipeline/core/irl_engine.py
rust_crate_pipeline/core/sacred_chain.py
rust_crate_pipeline/ml/__init__.py
rust_crate_pipeline/ml/artifacts.py
rust_crate_pipeline/ml/quality_predictor.py
rust_crate_pipeline/quality/__init__.py
rust_crate_pipeline/quality/heuristics.py
rust_crate_pipeline/scraping/__init__.py
rust_crate_pipeline/scraping/unified_scraper.py
rust_crate_pipeline/utils/__init__.py
rust_crate_pipeline/utils/canonical_store.py
rust_crate_pipeline/utils/code_example_quality.py
rust_crate_pipeline/utils/documentation_analyzer.py
rust_crate_pipeline/utils/ecosystem_analyzer.py
rust_crate_pipeline/utils/file_utils.py
rust_crate_pipeline/utils/http_client_utils.py
rust_crate_pipeline/utils/http_session.py
rust_crate_pipeline-4.1.0.dist-info/licenses/LICENSE
rust_crate_pipeline-4.1.0.dist-info/METADATA
rust_crate_pipeline-4.1.0.dist-info/WHEEL
rust_crate_pipeline-4.1.0.dist-info/entry_points.txt
rust_crate_pipeline-4.1.0.dist-info/top_level.txt
rust_crate_pipeline-4.1.0.dist-info/RECORD
