Metadata-Version: 2.4
Name: rust-crate-pipeline
Version: 4.1.0
Summary: A comprehensive system for gathering, enriching, and analyzing metadata for Rust crates using AI-powered insights, advanced caching, machine learning predictions, and modular architecture.
Home-page: https://github.com/Superuser666-Sigil/SigilDERG-Data_Production
Author: SuperUser666-Sigil
Author-email: SuperUser666-Sigil <miragemodularframework@gmail.com>
Maintainer-email: SuperUser666-Sigil <miragemodularframework@gmail.com>
Project-URL: Homepage, https://github.com/Superuser666-Sigil/SigilDERG-Data_Production
Project-URL: Documentation, https://github.com/Superuser666-Sigil/SigilDERG-Data_Production/wiki
Project-URL: Repository, https://github.com/Superuser666-Sigil/SigilDERG-Data_Production
Project-URL: Bug Tracker, https://github.com/Superuser666-Sigil/SigilDERG-Data_Production/issues
Project-URL: Release Notes, https://github.com/Superuser666-Sigil/SigilDERG-Data_Production/releases
Keywords: rust,crate,analysis,ai,llm,pipeline,caching,ml
Classifier: Development Status :: 5 - Production/Stable
Classifier: Intended Audience :: Developers
Classifier: Operating System :: OS Independent
Classifier: Programming Language :: Python :: 3
Classifier: Programming Language :: Python :: 3.12
Classifier: Topic :: Software Development :: Libraries :: Python Modules
Classifier: Topic :: Software Development :: Quality Assurance
Classifier: Topic :: System :: Distributed Computing
Classifier: Topic :: System :: Monitoring
Requires-Python: >=3.12
License-File: LICENSE
Requires-Dist: requests<3.0.0,>=2.31.0
Requires-Dist: aiohttp<4.0.0,>=3.9.0
Requires-Dist: pydantic<3.0.0,>=2.5.0
Requires-Dist: pydantic-settings<3.0.0,>=2.1.0
Requires-Dist: python-dotenv<2.0.0,>=1.0.0
Requires-Dist: click<9.0.0,>=8.1.0
Requires-Dist: rich<14.0.0,>=13.7.0
Requires-Dist: tqdm<5.0.0,>=4.66.0
Requires-Dist: psutil<7.0.0,>=6.1.1
Requires-Dist: humanize<5.0.0,>=4.8.0
Requires-Dist: colorama<1.0.0,>=0.4.6
Requires-Dist: termcolor<3.0.0,>=2.3.0
Requires-Dist: tabulate<1.0.0,>=0.9.0
Requires-Dist: asyncio-throttle<2.0.0,>=1.0.0
Requires-Dist: tenacity<9.0.0,>=8.2.0
Requires-Dist: structlog<24.0.0,>=23.2.0
Requires-Dist: marshmallow<4.0.0,>=3.20.0
Requires-Dist: cerberus<2.0.0,>=1.3.0
Requires-Dist: pathspec<1.0.0,>=0.11.0
Requires-Dist: watchdog<4.0.0,>=3.0.0
Requires-Dist: httpx<1.0.0,>=0.25.0
Requires-Dist: urllib3<3.0.0,>=2.0.0
Requires-Dist: orjson<4.0.0,>=3.9.0
Requires-Dist: ujson<6.0.0,>=5.8.0
Requires-Dist: python-dateutil<3.0.0,>=2.8.0
Requires-Dist: pytz<2024.0,>=2023.3
Requires-Dist: pyyaml<7.0.0,>=6.0.0
Requires-Dist: jsonschema<5.0.0,>=4.20.0
Requires-Dist: toml<1.0.0,>=0.10.0
Provides-Extra: web
Requires-Dist: crawl4ai<1.0.0,>=0.6.0; extra == "web"
Requires-Dist: playwright<2.0.0,>=1.40.0; extra == "web"
Requires-Dist: beautifulsoup4<5.0.0,>=4.12.0; extra == "web"
Requires-Dist: lxml<6.0.0,>=5.3.0; extra == "web"
Provides-Extra: ai
Requires-Dist: openai<2.0.0,>=1.3.0; extra == "ai"
Requires-Dist: anthropic<1.0.0,>=0.7.0; extra == "ai"
Requires-Dist: litellm<2.0.0,>=1.30.0; extra == "ai"
Requires-Dist: llama-cpp-python<1.0.0,>=0.2.0; extra == "ai"
Requires-Dist: tiktoken<1.0.0,>=0.5.0; extra == "ai"
Provides-Extra: ml
Requires-Dist: scikit-learn<2.0.0,>=1.3.0; extra == "ml"
Requires-Dist: numpy<2.0.0,>=1.24.0; extra == "ml"
Requires-Dist: pandas<3.0.0,>=2.0.0; extra == "ml"
Provides-Extra: caching
Requires-Dist: cachetools<6.0.0,>=5.3.0; extra == "caching"
Requires-Dist: aiofiles<25.0.0,>=24.1.0; extra == "caching"
Requires-Dist: redis<6.0.0,>=5.0.0; extra == "caching"
Requires-Dist: requests-cache<2.0.0,>=1.1.1; extra == "caching"
Provides-Extra: microservices
Requires-Dist: PyJWT<3.0.0,>=2.8.0; extra == "microservices"
Requires-Dist: prometheus-client<1.0.0,>=0.17.0; extra == "microservices"
Requires-Dist: asyncio-mqtt<1.0.0,>=0.16.0; extra == "microservices"
Provides-Extra: security
Requires-Dist: presidio-analyzer<3.0.0,>=2.2.0; extra == "security"
Requires-Dist: presidio-anonymizer<3.0.0,>=2.2.0; extra == "security"
Requires-Dist: spacy<4.0.0,>=3.7.0; extra == "security"
Requires-Dist: bandit<2.0.0,>=1.7.0; extra == "security"
Requires-Dist: safety<2.4.0,>=2.3.0; extra == "security"
Provides-Extra: analysis
Requires-Dist: textstat<1.0.0,>=0.7.0; extra == "analysis"
Requires-Dist: vaderSentiment<4.0.0,>=3.3.0; extra == "analysis"
Requires-Dist: textblob<1.0.0,>=0.17.0; extra == "analysis"
Provides-Extra: http2
Requires-Dist: h2<5.0.0,>=3.0.0; extra == "http2"
Requires-Dist: hpack<5.0.0,>=4.0.0; extra == "http2"
Requires-Dist: hyperframe<7.0.0,>=6.0.0; extra == "http2"
Provides-Extra: all
Requires-Dist: crawl4ai<1.0.0,>=0.6.0; extra == "all"
Requires-Dist: playwright<2.0.0,>=1.40.0; extra == "all"
Requires-Dist: beautifulsoup4<5.0.0,>=4.12.0; extra == "all"
Requires-Dist: lxml<6.0.0,>=5.3.0; extra == "all"
Requires-Dist: openai<2.0.0,>=1.3.0; extra == "all"
Requires-Dist: anthropic<1.0.0,>=0.7.0; extra == "all"
Requires-Dist: litellm<2.0.0,>=1.30.0; extra == "all"
Requires-Dist: llama-cpp-python<1.0.0,>=0.2.0; extra == "all"
Requires-Dist: tiktoken<1.0.0,>=0.5.0; extra == "all"
Requires-Dist: scikit-learn<2.0.0,>=1.3.0; extra == "all"
Requires-Dist: numpy<2.0.0,>=1.24.0; extra == "all"
Requires-Dist: pandas<3.0.0,>=2.0.0; extra == "all"
Requires-Dist: cachetools<6.0.0,>=5.3.0; extra == "all"
Requires-Dist: aiofiles<25.0.0,>=24.1.0; extra == "all"
Requires-Dist: redis<6.0.0,>=5.0.0; extra == "all"
Requires-Dist: requests-cache<2.0.0,>=1.1.1; extra == "all"
Requires-Dist: PyJWT<3.0.0,>=2.8.0; extra == "all"
Requires-Dist: prometheus-client<1.0.0,>=0.17.0; extra == "all"
Requires-Dist: asyncio-mqtt<1.0.0,>=0.16.0; extra == "all"
Requires-Dist: presidio-analyzer<3.0.0,>=2.2.0; extra == "all"
Requires-Dist: presidio-anonymizer<3.0.0,>=2.2.0; extra == "all"
Requires-Dist: spacy<4.0.0,>=3.7.0; extra == "all"
Requires-Dist: bandit<2.0.0,>=1.7.0; extra == "all"
Requires-Dist: safety<2.4.0,>=2.3.0; extra == "all"
Requires-Dist: h2<5.0.0,>=3.0.0; extra == "all"
Requires-Dist: hpack<5.0.0,>=4.0.0; extra == "all"
Requires-Dist: hyperframe<7.0.0,>=6.0.0; extra == "all"
Provides-Extra: dev
Requires-Dist: pytest<8.0.0,>=7.4.0; extra == "dev"
Requires-Dist: pytest-asyncio<1.0.0,>=0.21.0; extra == "dev"
Requires-Dist: pytest-cov<5.0.0,>=4.1.0; extra == "dev"
Requires-Dist: pytest-mock<4.0.0,>=3.11.0; extra == "dev"
Requires-Dist: black<24.0.0,>=23.7.0; extra == "dev"
Requires-Dist: flake8<7.0.0,>=6.0.0; extra == "dev"
Requires-Dist: mypy<2.0.0,>=1.5.0; extra == "dev"
Requires-Dist: isort<6.0.0,>=5.12.0; extra == "dev"
Requires-Dist: pre-commit<4.0.0,>=3.3.0; extra == "dev"
Requires-Dist: sphinx<8.0.0,>=7.1.0; extra == "dev"
Requires-Dist: sphinx-rtd-theme<2.0.0,>=1.3.0; extra == "dev"
Requires-Dist: myst-parser<3.0.0,>=2.0.0; extra == "dev"
Requires-Dist: types-toml>=0.10.8; extra == "dev"
Requires-Dist: types-tqdm>=4.67.0; extra == "dev"
Requires-Dist: pandas-stubs>=2.3.0; extra == "dev"
Requires-Dist: types-aiofiles>=24.1.0; extra == "dev"
Requires-Dist: types-cachetools>=6.1.0; extra == "dev"
Provides-Extra: test
Requires-Dist: pytest<8.0.0,>=7.4.0; extra == "test"
Requires-Dist: pytest-asyncio<1.0.0,>=0.21.0; extra == "test"
Requires-Dist: pytest-cov<5.0.0,>=4.1.0; extra == "test"
Requires-Dist: pytest-mock<4.0.0,>=3.11.0; extra == "test"
Provides-Extra: docs
Requires-Dist: sphinx<8.0.0,>=7.1.0; extra == "docs"
Requires-Dist: sphinx-rtd-theme<2.0.0,>=1.3.0; extra == "docs"
Requires-Dist: myst-parser<3.0.0,>=2.0.0; extra == "docs"
Dynamic: author
Dynamic: home-page
Dynamic: license-file
Dynamic: requires-python
